MANIFEST.in
README.md
requirements.txt
setup.py
ubackup/VERSION.txt
ubackup/__init__.py
ubackup/log.py
ubackup/manager.py
ubackup/settings.py
ubackup/utils.py
ubackup.egg-info/PKG-INFO
ubackup.egg-info/SOURCES.txt
ubackup.egg-info/dependency_links.txt
ubackup.egg-info/entry_points.txt
ubackup.egg-info/not-zip-safe
ubackup.egg-info/requires.txt
ubackup.egg-info/top_level.txt
ubackup/backup/__init__.py
ubackup/backup/base.py
ubackup/backup/mysql.py
ubackup/backup/path.py
ubackup/backup/postgresql.py
ubackup/backup/zfs.py
ubackup/bucket/__init__.py
ubackup/bucket/base.py
ubackup/bucket/dropbox.py
ubackup/bucket/local.py
ubackup/cli/__init__.py
ubackup/cli/utils.py
ubackup/cli/validators.py
ubackup/cli/actions/__init__.py
ubackup/cli/actions/mysql.py
ubackup/cli/actions/path.py
ubackup/cli/actions/postgresql.py
ubackup/tests/__init__.py
ubackup/tests/test_backup.py
ubackup/tests/test_bucket.py
ubackup/tests/test_cli.py
ubackup/tests/test_manager.py
ubackup/tests/test_utils.py
ubackup/tests/test_validators.py