Metadata-Version: 1.0
Name: ubackup
Version: 0.1.5
Summary: Minimalist backup tool
Home-page: https://github.com/ThomasKliszowski/ubackup
Author: Thomas Kliszowski
Author-email: contact@thomaskliszowski.fr
License: MIT
Keywords: ubackup backup tool
Platform: UNKNOWN
